blanken/__init__.py
blanken/__main__.py
blanken/enforcer.py
blanken-0.1.2.dist-info/licenses/LICENSE
blanken-0.1.2.dist-info/METADATA
blanken-0.1.2.dist-info/WHEEL
blanken-0.1.2.dist-info/entry_points.txt
blanken-0.1.2.dist-info/top_level.txt
blanken-0.1.2.dist-info/RECORD
